django_redis_ex/__init__.py
django_redis_ex/async_cache.py
django_redis_ex/cache.py
django_redis_ex-1.0.0.dist-info/METADATA
django_redis_ex-1.0.0.dist-info/WHEEL
django_redis_ex-1.0.0.dist-info/licenses/LICENSE
django_redis_ex-1.0.0.dist-info/RECORD
