Metadata-Version: 2.3
Name: django_redis_ex
Version: 1.0.0
Summary: Async and sync Redis cache backend for Django.
Project-URL: Homepage, https://github.com/gojuukaze/django-redis-ex
Project-URL: Issues, https://github.com/gojuukaze/django-redis-ex/issues
Author-email: gojuukaze <ikaze_email@163.com>
License-File: LICENSE
Classifier: Development Status :: 4 - Beta
Classifier: Framework :: Django
Classifier: License :: OSI Approved :: GNU General Public License v3 (GPLv3)
Classifier: Operating System :: OS Independent
Classifier: Programming Language :: Python :: 3
Requires-Python: >=3.8
Requires-Dist: django>=4.0
Requires-Dist: redis>=4.2.0
